tests
django_runtests
