Metadata-Version: 1.0
Name: django-runtests
Version: 0.4.0
Summary: A base framework to write a simple runtests.py script for django apps.
Home-page: http://github.com/rbarrois/django-runtests
Author: Raphaël Barrois
Author-email: raphael.barrois@polytechnique.org
License: MIT
Download-URL: http://pypi.python.org/pypi/django-runtests/
Keywords: django,test,runtests,test runner
Platform: UNKNOWN
Classifier: Development Status :: 4 - Beta
Classifier: Intended Audience :: Developers
Classifier: License :: OSI Approved :: MIT License
Classifier: Topic :: Software Development :: Libraries :: Python Modules
Classifier: Operating System :: OS Independent
Classifier: Programming Language :: Python
